[{"maalID":"item()?['cr6b6_pln_goalid']","maalNavn":"item()?['cr6b6_pln_goalname']","maalType":"item()?['cr6b6_pln_goaltype']","maalOverordnet":"item()?['_cr6b6_overordnetmal_value']","maalPlan":"item()?['_cr6b6_plan_value']"},{"maalID":"item()?['cr6b6_pln_goalid']","maalNavn":"item()?['cr6b6_pln_goalname']","maalType":"item()?['cr6b6_pln_goaltype']","maalOverordnet":"item()?['_cr6b6_overordnetmal_value']","maalPlan":"item()?['_cr6b6_plan_value']"},{"maalID":"item()?['cr6b6_pln_goalid']","maalNavn":"item()?['cr6b6_pln_goalname']","maalType":"item()?['cr6b6_pln_goaltype']","maalOverordnet":"item()?['_cr6b6_overordnetmal_value']","maalPlan":"item()?['_cr6b6_plan_value']"},{"maalID":"item()?['cr6b6_pln_goalid']","maalNavn":"item()?['cr6b6_pln_goalname']","maalType":"item()?['cr6b6_pln_goaltype']","maalOverordnet":"item()?['_cr6b6_overordnetmal_value']","maalPlan":"item()?['_cr6b6_plan_value']"},{"maalID":"item()?['cr6b6_pln_goalid']","maalNavn":"item()?['cr6b6_pln_goalname']","maalType":"item()?['cr6b6_pln_goaltype']","maalOverordnet":"item()?['_cr6b6_overordnetmal_value']","maalPlan":"item()?['_cr6b6_plan_value']"},{"maalID":"item()?['cr6b6_pln_goalid']","maalNavn":"item()?['cr6b6_pln_goalname']","maalType":"item()?['cr6b6_pln_goaltype']","maalOverordnet":"item()?['_cr6b6_overordnetmal_value']","maalPlan":"item()?['_cr6b6_plan_value']"},{"maalID":"item()?['cr6b6_pln_goalid']","maalNavn":"item()?['cr6b6_pln_goalname']","maalType":"item()?['cr6b6_pln_goaltype']","maalOverordnet":"item()?['_cr6b6_overordnetmal_value']","maalPlan":"item()?['_cr6b6_plan_value']"},{"maalID":"item()?['cr6b6_pln_goalid']","maalNavn":"item()?['cr6b6_pln_goalname']","maalType":"item()?['cr6b6_pln_goaltype']","maalOverordnet":"item()?['_cr6b6_overordnetmal_value']","maalPlan":"item()?['_cr6b6_plan_value']"},{"maalID":"item()?['cr6b6_pln_goalid']","maalNavn":"item()?['cr6b6_pln_goalname']","maalType":"item()?['cr6b6_pln_goaltype']","maalOverordnet":"item()?['_cr6b6_overordnetmal_value']","maalPlan":"item()?['_cr6b6_plan_value']"},{"maalID":"item()?['cr6b6_pln_goalid']","maalNavn":"item()?['cr6b6_pln_goalname']","maalType":"item()?['cr6b6_pln_goaltype']","maalOverordnet":"item()?['_cr6b6_overordnetmal_value']","maalPlan":"item()?['_cr6b6_plan_value']"},{"maalID":"item()?['cr6b6_pln_goalid']","maalNavn":"item()?['cr6b6_pln_goalname']","maalType":"item()?['cr6b6_pln_goaltype']","maalOverordnet":"item()?['_cr6b6_overordnetmal_value']","maalPlan":"item()?['_cr6b6_plan_value']"},{"maalID":"item()?['cr6b6_pln_goalid']","maalNavn":"item()?['cr6b6_pln_goalname']","maalType":"item()?['cr6b6_pln_goaltype']","maalOverordnet":"item()?['_cr6b6_overordnetmal_value']","maalPlan":"item()?['_cr6b6_plan_value']"},{"maalID":"item()?['cr6b6_pln_goalid']","maalNavn":"item()?['cr6b6_pln_goalname']","maalType":"item()?['cr6b6_pln_goaltype']","maalOverordnet":"item()?['_cr6b6_overordnetmal_value']","maalPlan":"item()?['_cr6b6_plan_value']"},{"maalID":"item()?['cr6b6_pln_goalid']","maalNavn":"item()?['cr6b6_pln_goalname']","maalType":"item()?['cr6b6_pln_goaltype']","maalOverordnet":"item()?['_cr6b6_overordnetmal_value']","maalPlan":"item()?['_cr6b6_plan_value']"},{"maalID":"item()?['cr6b6_pln_goalid']","maalNavn":"item()?['cr6b6_pln_goalname']","maalType":"item()?['cr6b6_pln_goaltype']","maalOverordnet":"item()?['_cr6b6_overordnetmal_value']","maalPlan":"item()?['_cr6b6_plan_value']"},{"maalID":"item()?['cr6b6_pln_goalid']","maalNavn":"item()?['cr6b6_pln_goalname']","maalType":"item()?['cr6b6_pln_goaltype']","maalOverordnet":"item()?['_cr6b6_overordnetmal_value']","maalPlan":"item()?['_cr6b6_plan_value']"},{"maalID":"item()?['cr6b6_pln_goalid']","maalNavn":"item()?['cr6b6_pln_goalname']","maalType":"item()?['cr6b6_pln_goaltype']","maalOverordnet":"item()?['_cr6b6_overordnetmal_value']","maalPlan":"item()?['_cr6b6_plan_value']"},{"maalID":"item()?['cr6b6_pln_goalid']","maalNavn":"item()?['cr6b6_pln_goalname']","maalType":"item()?['cr6b6_pln_goaltype']","maalOverordnet":"item()?['_cr6b6_overordnetmal_value']","maalPlan":"item()?['_cr6b6_plan_value']"},{"maalID":"item()?['cr6b6_pln_goalid']","maalNavn":"item()?['cr6b6_pln_goalname']","maalType":"item()?['cr6b6_pln_goaltype']","maalOverordnet":"item()?['_cr6b6_overordnetmal_value']","maalPlan":"item()?['_cr6b6_plan_value']"},{"maalID":"item()?['cr6b6_pln_goalid']","maalNavn":"item()?['cr6b6_pln_goalname']","maalType":"item()?['cr6b6_pln_goaltype']","maalOverordnet":"item()?['_cr6b6_overordnetmal_value']","maalPlan":"item()?['_cr6b6_plan_value']"},{"maalID":"item()?['cr6b6_pln_goalid']","maalNavn":"item()?['cr6b6_pln_goalname']","maalType":"item()?['cr6b6_pln_goaltype']","maalOverordnet":"item()?['_cr6b6_overordnetmal_value']","maalPlan":"item()?['_cr6b6_plan_value']"},{"maalID":"item()?['cr6b6_pln_goalid']","maalNavn":"item()?['cr6b6_pln_goalname']","maalType":"item()?['cr6b6_pln_goaltype']","maalOverordnet":"item()?['_cr6b6_overordnetmal_value']","maalPlan":"item()?['_cr6b6_plan_value']"}]